<annotation>
	<folder></folder>
	<filename>Bottle31_jpg.rf.8837642f86f12f3e64b1a6003ea4b0d5.jpg</filename>
	<path>Bottle31_jpg.rf.8837642f86f12f3e64b1a6003ea4b0d5.jpg</path>
	<source>
		<database>roboflow.com</database>
	</source>
	<size>
		<width>640</width>
		<height>640</height>
		<depth>3</depth>
	</size>
	<segmented>0</segmented>
	<object>
		<name>Non-biodegradable</name>
		<pose>Unspecified</pose>
		<truncated>0</truncated>
		<difficult>0</difficult>
		<occluded>0</occluded>
		<bndbox>
			<xmin>55</xmin>
			<xmax>557</xmax>
			<ymin>74</ymin>
			<ymax>461</ymax>
		</bndbox>
	</object>
</annotation>
